datapurge/__init__.py
datapurge/compat.py
datapurge/exceptions.py
datapurge/models.py
datapurge/settings.py
datapurge/tests.py
datapurge/views.py
datapurge/management/__init__.py
datapurge/management/commands/__init__.py
datapurge/management/commands/purge.py
datapurge/purge/__init__.py
datapurge/purge/actions.py
datapurge/purge/policies.py
datapurge/purge/tasks.py
datapurge/runtests/__init__.py
datapurge/runtests/runtests.py
datapurge/runtests/settings.py
datapurge/runtests/urls.py
django_datapurge-0.0.2.dist-info/DESCRIPTION.rst
django_datapurge-0.0.2.dist-info/METADATA
django_datapurge-0.0.2.dist-info/RECORD
django_datapurge-0.0.2.dist-info/WHEEL
django_datapurge-0.0.2.dist-info/metadata.json
django_datapurge-0.0.2.dist-info/top_level.txt
